[
    {
        "id" : 1,
        "title" : "",
        "artist" : "",
        "link"  ""
    }
    {
        "id" : 2,
        "title" : "",
        "artist" : "",
        "link"  ""
    }
    {
        "id" : 3,
        "title" : "",
        "artist" : "",
        "link"  ""
    }
    {
        "id" : 4,
        "title" : "",
        "artist" : "",
        "link"  ""
    }
    {
        "id" : 5,
        "title" : "",
        "artist" : "",
        "link"  ""
    }
    {
        "id" : 6,
        "title" : "",
        "artist" : "",
        "link"  ""
    }
]